A1/Q6/Part B/randommessage.v
//Mishal Shah
//16CO125
//Random message generation
//16 Oct 2017

module A(output reg[3:0] message_out,input[3:0][3:0] message_in,input clock);
    reg[3:0] rnd=3'b000;                         //random is set as 0
    always@(posedge clock) begin
        if(rnd==3'b000) begin
            rnd <= {$random}%16+1;               //random is changed
            message_out <= {$random}%8;          //random msg sent by A
            $display("Time:%0t\nA sent %b to B",$time,message_out);         //msg displayed
            $display("B responded with %b %b %b %b\n",message_in[0],message_in[1],message_in[2],message_in[3]);    //msg recieved displayed                            
        end 
        else begin
            rnd <= rnd - 1;  //random variable decremented to send msg at random interval
        end
        
    end
endmodule

module B(output reg[3:0][3:0] message_out,input[3:0] message_in,input clock);
    always@(posedge clock) begin
        if(message_in !== 4'bzzzz) begin
            message_out[0] <= {$random}%16;            //random msg generated by B
            message_out[1] <= {$random}%16;
            message_out[2] <= {$random}%16;
            message_out[3] <= {$random}%16;
        end
    end
endmodule

Assignment1/Q6/Part B/t_randommessage.v
//Mishal Shah
//16CO125
//Test bench for random msg generattion
//16 Oct 2017
    module t_q6b;
    reg clock=0;
    wire[3:0] message1_out;
    wire[3:0][3:0]  message2_out;
    
    A m1(message1_out,message2_out,clock);          //instance of modules
    B m2(message2_out,message1_out,clock);
    
    always begin                        //set up clock
        #5 clock = ~clock;
    end
    initial begin
        $dumpfile("randommessage.vcd");   //gtkwave generation
        $dumpvars(0,t_q6b); 
        #500 $finish;
    end
endmodule

Assignment1/Q6/Part B/randommessage.vcd
$date
	Tue Oct 17 16:22:53 2017
$end
$version
	Icarus Verilog
$end
$timescale
	1s
$end
$scope module t_q6b $end
$var wire 16 ! message2_out [15:0] $end
$var wire 4 " message1_out [3:0] $end
$var reg 1 # clock $end
$scope module m1 $end
$var wire 1 # clock $end
$var wire 16 $ message_in [15:0] $end
$var reg 4 % message_out [3:0] $end
$var reg 4 & rnd [3:0] $end
$upscope $end
$scope module m2 $end
$var wire 1 # clock $end
$var wire 4 ' message_in [3:0] $end
$var reg 16 ( message_out [15:0] $end
$upscope $end
$upscope $end
$enddefinitions $end
#0
$dumpvars
bx (
bx '
b0 &
bx %
bx $
0#
bx "
bx !
$end
#5
b101 "
b101 %
b101 '
b1110 &
b11100100010100 !
b11100100010100 $
b11100100010100 (
1#
#10
0#
#15
b1101000100100101 !
b1101000100100101 $
b1101000100100101 (
b1101 &
1#
#20
0#
#25
b1100 &
b1100110111010110 !
b1100110111010110 $
b1100110111010110 (
1#
#30
0#
#35
b1010010101101001 !
b1010010101101001 $
b1010010101101001 (
b1011 &
1#
#40
0#
#45
b1010 &
b1111001001110101 !
b1111001001110101 $
b1111001001110101 (
1#
#50
0#
#55
b101100011100010 !
b101100011100010 $
b101100011100010 (
b1001 &
1#
#60
0#
#65
b1000 &
b101110111011100 !
b101110111011100 $
b101110111011100 (
1#
#70
0#
#75
b10100011 !
b10100011 $
b10100011 (
b111 &
1#
#80
0#
#85
b110 &
b11011011011010 !
b11011011011010 $
b11011011011010 (
1#
#90
0#
#95
b101101100111101 !
b101101100111101 $
b101101100111101 (
b101 &
1#
#100
0#
#105
b100 &
b1111110111100010 !
b1111110111100010 $
b1111110111100010 (
1#
#110
0#
#115
b1100101010100011 !
b1100101010100011 $
b1100101010100011 (
b11 &
1#
#120
0#
#125
b10 &
b1000000110100010 !
b1000000110100010 $
b1000000110100010 (
1#
#130
0#
#135
b110101110011000 !
b110101110011000 $
b110101110011000 (
b1 &
1#
#140
0#
#145
b0 &
b1010110011100110 !
b1010110011100110 $
b1010110011100110 (
1#
#150
0#
#155
b1010101111110101 !
b1010101111110101 $
b1010101111110101 (
b1 "
b1 %
b1 '
b1100 &
1#
#160
0#
#165
b1011 &
b1001000101011110 !
b1001000101011110 $
b1001000101011110 (
1#
#170
0#
#175
b1111111111000010 !
b1111111111000010 $
b1111111111000010 (
b1010 &
1#
#180
0#
#185
b1001 &
b1100111101111000 !
b1100111101111000 $
b1100111101111000 (
1#
#190
0#
#195
b100110011011 !
b100110011011 $
b100110011011 (
b1000 &
1#
#200
0#
#205
b111 &
b1100011000010111 !
b1100011000010111 $
b1100011000010111 (
1#
#210
0#
#215
b1101011110000010 !
b1101011110000010 $
b1101011110000010 (
b110 &
1#
#220
0#
#225
b101 &
b1001110111100010 !
b1001110111100010 $
b1001110111100010 (
1#
#230
0#
#235
b1000010100111111 !
b1000010100111111 $
b1000010100111111 (
b100 &
1#
#240
0#
#245
b11 &
b1010111110011011 !
b1010111110011011 $
b1010111110011011 (
1#
#250
0#
#255
b1100111001101000 !
b1100111001101000 $
b1100111001101000 (
b10 &
1#
#260
0#
#265
b1 &
b11001101101010 !
b11001101101010 $
b11001101101010 (
1#
#270
0#
#275
b100111100111111 !
b100111100111111 $
b100111100111111 (
b0 &
1#
#280
0#
#285
b101 "
b101 %
b101 '
b1010 &
b1010011010110111 !
b1010011010110111 $
b1010011010110111 (
1#
#290
0#
#295
b1111010101011010 !
b1111010101011010 $
b1111010101011010 (
b1001 &
1#
#300
0#
#305
b1000 &
b1010000001001001 !
b1010000001001001 $
b1010000001001001 (
1#
#310
0#
#315
b1010110011101011 !
b1010110011101011 $
b1010110011101011 (
b111 &
1#
#320
0#
#325
b110 &
b1110011000111101 !
b1110011000111101 $
b1110011000111101 (
1#
#330
0#
#335
b1000011010100111 !
b1000011010100111 $
b1000011010100111 (
b101 &
1#
#340
0#
#345
b100 &
b11010010001001 !
b11010010001001 $
b11010010001001 (
1#
#350
0#
#355
b1101101110010100 !
b1101101110010100 $
b1101101110010100 (
b11 &
1#
#360
0#
#365
b10 &
b1010011011011001 !
b1010011011011001 $
b1010011011011001 (
1#
#370
0#
#375
b100011001010110 !
b100011001010110 $
b100011001010110 (
b1 &
1#
#380
0#
#385
b0 &
b1000010010010111 !
b1000010010010111 $
b1000010010010111 (
1#
#390
0#
#395
b1100100011100111 !
b1100100011100111 $
b1100100011100111 (
b1001 &
1#
#400
0#
#405
b1000 &
b110110010011101 !
b110110010011101 $
b110110010011101 (
1#
#410
0#
#415
b11011011010 !
b11011011010 $
b11011011010 (
b111 &
1#
#420
0#
#425
b110 &
b1010111010100011 !
b1010111010100011 $
b1010111010100011 (
1#
#430
0#
#435
b111100110100101 !
b111100110100101 $
b111100110100101 (
b101 &
1#
#440
0#
#445
b100 &
b110011000000110 !
b110011000000110 $
b110011000000110 (
1#
#450
0#
#455
b1000011011001101 !
b1000011011001101 $
b1000011011001101 (
b11 &
1#
#460
0#
#465
b10 &
b1001111110111110 !
b1001111110111110 $
b1001111110111110 (
1#
#470
0#
#475
b1011100011010 !
b1011100011010 $
b1011100011010 (
b1 &
1#
#480
0#
#485
b0 &
b101010100000110 !
b101010100000110 $
b101010100000110 (
1#
#490
0#
#495
b11101110000101 !
b11101110000101 $
b11101110000101 (
b1 "
b1 %
b1 '
b1010 &
1#
