Assignment1/Q2/encoder.v
//Samyak Jain
//16CO254
//16X4 Encoder
//14 Oct 2017

module encoder(a,d,E);
output [3:0]a;
input [15:0]d;
input E;
wire t1,t2,t3,t4;
  or(t1,d[8],d[9],d[10],d[11],d[12],d[13],d[14],d[15]),
    (t2,d[4],d[5],d[6],d[7],d[12],d[13],d[14],d[15]),
    (t3,d[2],d[3],d[6],d[7],d[10],d[11],d[14],d[15]),
    (t4,d[1],d[3],d[5],d[7],d[9],d[11],d[13],d[15]);
 and(a[3],t1,E),
    (a[2],t2,E),
    (a[1],t3,E),
    (a[0],t4,E);
    
endmodule

Assignment1/Q2/t_encoder.v
//Samyak Jain
//16CO254
//Testbench for 16X4 encoder
//14 Oct 2017

`timescale 1ns/1ps

module test;
wire [3:0]a;
reg [15:0]d;
reg E;

encoder ef(a,d,E);
integer i;
initial begin              //to create gtkwave 
	$dumpfile("Encoder.vcd");
	$dumpvars(0,test);
end

initial begin
	E=1'b1;
for(i=0;i<=15;i++)    //loop to generate desired input
 	begin
 		d=0;
	 	d[i]=1;
 	#20;
 	end
end

initial begin              //displaying desired values
	$monitor("input=%b%b%b%b%b%b%b%b%b%b%b%b%b%b%b%b output=%b%b%b%b",d[15],d[14],d[13],d[12],d[11],d[10],d[9],d[8],d[7],d[6],d[5],d[4],d[3],d[2],d[1],d[0],a[3],a[2],a[1],a[0]);

#300 $finish;        //after every 20 ns input changes and there are 15 combination of input so after 300 ns program terminates
end
endmodule

A1/Q2/Decoder.vcd
$date
	Sat Oct 14 20:20:18 2017
$end
$version
	Icarus Verilog
$end
$timescale
	1ps
$end
$scope module test $end
$var wire 4 ! a [3:0] $end
$var reg 1 " E $end
$var reg 16 # d [15:0] $end
$var integer 32 $ i [31:0] $end
$scope module ef $end
$var wire 1 " E $end
$var wire 16 % d [15:0] $end
$var wire 1 & t1 $end
$var wire 1 ' t2 $end
$var wire 1 ( t3 $end
$var wire 1 ) t4 $end
$var wire 4 * a [3:0] $end
$upscope $end
$upscope $end
$enddefinitions $end
#0
$dumpvars
b0 *
0)
0(
0'
0&
b1 %
b0 $
b1 #
1"
b0 !
$end
#20000
b1 !
b1 *
1)
b10 #
b10 %
b1 $
#40000
b10 !
b10 *
1(
0)
b100 #
b100 %
b10 $
#60000
b11 !
b11 *
1)
b1000 #
b1000 %
b11 $
#80000
b100 !
b100 *
1'
0(
0)
b10000 #
b10000 %
b100 $
#100000
b101 !
b101 *
1)
b100000 #
b100000 %
b101 $
#120000
b110 !
b110 *
1(
0)
b1000000 #
b1000000 %
b110 $
#140000
b111 !
b111 *
1)
b10000000 #
b10000000 %
b111 $
#160000
b1000 !
b1000 *
1&
0'
0(
0)
b100000000 #
b100000000 %
b1000 $
#180000
b1001 !
b1001 *
1)
b1000000000 #
b1000000000 %
b1001 $
#200000
b1010 !
b1010 *
1(
0)
b10000000000 #
b10000000000 %
b1010 $
#220000
b1011 !
b1011 *
1)
b100000000000 #
b100000000000 %
b1011 $
#240000
b1100 !
b1100 *
1'
0(
0)
b1000000000000 #
b1000000000000 %
b1100 $
#260000
b1101 !
b1101 *
1)
b10000000000000 #
b10000000000000 %
b1101 $
#280000
b1110 !
b1110 *
1(
0)
b100000000000000 #
b100000000000000 %
b1110 $
#300000
b1111 !
b1111 *
1)
b1000000000000000 #
b1000000000000000 %
b1111 $
#320000
b10000 $
