A2/ALU/ALU.v
/*
Samyak Jain & Mishal Shah
16CO254 & 16CO125
29/10/2017
1 bit ALU 
*/
module ALU_1_bit(result,zero_flag,a,b,Ainvert,Binvert,op,cy_in);

  output result,zero_flag;                         //Output declared as result and zero flag

  input a,b,Ainvert,Binvert,cy_in;                 //Input is a,b,Ainvert,Binvert,cy_in

  input [1:0]op;                                    //operation mux select lines

  wire _a,_b,_and,_or,_sum,_carry,less,t,less1;     //wires used in connection   

  FA f4(less1,t,a,b,1'b1);                          //Full Adder module called to subtract a and b 
  or(zero_flag,less1,1'b0);                         //zero-flag is set

  mux2 f1(Ainvert,a,~a,_a);                         //Now mux1 is called to select a or a'
  mux2 f2(Binvert,b,~b,_b);                         //mux2 is called to select b or b'

  and (_and,_a,_b);                                 //and operation done and wire _and sent to 00 of operation mux
  or (_or,_a,_b);                                   //or operation done and wire _or sent to 01 of operation mux

  FA f3(_sum,_carry,_a,_b,cy_in);                   //add/sub operation done and wire _sum sent to 10 of operation mux
  FA f6(less,t,_a,_b,1'b1);                         //slt operation done and wire less sent to 11 of operation mux

  mux4 f5(op,_and,_or,_sum,less,result);             //Operation mux is called

endmodule


module mux2(input select,a1,a2,output o);        //2x1 mux made with nand gates
  
  wire t1,t2;
  
  nand(t1,a1,~select);
  
  nand(t2,a2,select);
  
  nand(o,t1,t2);

endmodule


module mux4(select,a1,a2,a3,a4,o);              //4x1 mux made with nand gates
  
  input [1:0]select;

  input a1,a2,a3,a4;

  output o;

  wire t1,t2,t3,t4;

  nand(t1,a1,~select[1],~select[0]);

  nand(t2,a2,~select[1],select[0]);

  nand(t3,a3,select[1],~select[0]);

  nand(t4,a4,select[1],select[0]);

  nand(o,t1,t2,t3,t4);

endmodule


module FA(sum,cy_out,a,b,cy_in);             //Full adder module
  
  output sum,cy_out;
  
  input a,b,cy_in;
  
  wire t1,t2,t3;
  
  HA G1(t1,t2,a,b);                           //call the module halfadder
  
  HA G2(sum,t3,t1,cy_in);                     //again call the module halfadder
  
  or (cy_out,t3,t2);

endmodule


module HA(sum,cy_out,a,b);                 //Half Adder module

  output sum,cy_out;
  
  input a,b;
  
  xor (sum,a,b);                            //sum=a xor b, carry=a and b
  
  and (cy_out,a,b);

endmodule

A2/ALU/t_ALU.v
/*
Samyak Jain & Mishal Shah
16CO254 & 16CO125
29/10/2017
Test Bench for 1-bit ALU
*/
`timescale 1ns/1ps

module test;

wire result,zero_flag;           
reg a,b,Ainvert,Binvert,cy_in;
reg [1:0]op;

ALU_1_bit f5(result,zero_flag,a,b,Ainvert,Binvert,op,cy_in);      //ALU module called       

initial begin
$dumpfile("ALU.vcd");
$dumpvars(0,test);
end

initial begin

//Inputs set to perform AND Operation

$display("AND Operation");
a=1'b0;
b=1'b0;
Ainvert=1'b0;
Binvert=1'b0;
op=2'b00;
$monitor("a=%b b=%b Ainvert=%b Binvert=%b op=%b result=%b zero_flag=%b",a,b,Ainvert,Binvert,op,result,zero_flag);
#10;
a=1'b0;
b=1'b1;
Ainvert=1'b0;
Binvert=1'b0;
op=2'b00;
$monitor("a=%b b=%b Ainvert=%b Binvert=%b op=%b result=%b zero_flag=%b",a,b,Ainvert,Binvert,op,result,zero_flag);
#10;

a=1'b1;
b=1'b0;
Ainvert=1'b0;
Binvert=1'b0;
op=2'b00;
$monitor("a=%b b=%b Ainvert=%b Binvert=%b op=%b result=%b zero_flag=%b",a,b,Ainvert,Binvert,op,result,zero_flag);
#10;

a=1'b1;
b=1'b1;
Ainvert=1'b0;
Binvert=1'b0;
op=2'b00;
$monitor("a=%b b=%b Ainvert=%b Binvert=%b op=%b result=%b zero_flag=%b\n",a,b,Ainvert,Binvert,op,result,zero_flag);
#10;


//Inputs set to perform OR Operation



$display("For OR Operation");
a=1'b0;
b=1'b0;
Ainvert=1'b0;
Binvert=1'b0;
op=2'b01;
$monitor("a=%b b=%b Ainvert=%b Binvert=%b op=%b result=%b zero_flag=%b",a,b,Ainvert,Binvert,op,result,zero_flag);
#10;

a=1'b0;
b=1'b1;
Ainvert=1'b0;
Binvert=1'b0;
op=2'b01;
$monitor("a=%b b=%b Ainvert=%b Binvert=%b op=%b result=%b zero_flag=%b",a,b,Ainvert,Binvert,op,result,zero_flag);
#10;

a=1'b1;
b=1'b0;
Ainvert=1'b0;
Binvert=1'b0;
op=2'b01;
$monitor("a=%b b=%b Ainvert=%b Binvert=%b op=%b result=%b zero_flag=%b",a,b,Ainvert,Binvert,op,result,zero_flag);
#10;

a=1'b1;
b=1'b1;
Ainvert=1'b0;
Binvert=1'b0;
op=2'b01;
$monitor("a=%b b=%b Ainvert=%b Binvert=%b op=%b result=%b zero_flag=%b\n",a,b,Ainvert,Binvert,op,result,zero_flag);
#10;


//Inputs set to perform ADD Operation



$display("For ADD opeartion");
a=1'b0;
b=1'b0;
Ainvert=1'b0;
Binvert=1'b0;
cy_in=1'b0;
op=2'b10;
$monitor("a=%b b=%b Ainvert=%b Binvert=%b carry in=%b op=%b result=%b zero_flag=%b",a,b,Ainvert,Binvert,cy_in,op,result,zero_flag);
#10;
a=1'b0;
b=1'b1;
Ainvert=1'b0;
Binvert=1'b0;
cy_in=1'b0;
op=2'b10;
$monitor("a=%b b=%b Ainvert=%b Binvert=%b carry in=%b op=%b result=%b zero_flag=%b",a,b,Ainvert,Binvert,cy_in,op,result,zero_flag);
#10;
a=1'b1;
b=1'b0;
Ainvert=1'b0;
Binvert=1'b0;
cy_in=1'b0;
op=2'b10;
$monitor("a=%b b=%b Ainvert=%b Binvert=%b carry in=%b op=%b result=%b zero_flag=%b",a,b,Ainvert,Binvert,cy_in,op,result,zero_flag);
#10;
a=1'b1;
b=1'b1;
Ainvert=1'b0;
Binvert=1'b0;
cy_in=1'b0;
op=2'b10;
$monitor("a=%b b=%b Ainvert=%b Binvert=%b carry in=%b op=%b result=%b zero_flag=%b\n",a,b,Ainvert,Binvert,cy_in,op,result,zero_flag);
#10;



//Inputs set to perform SUB Operation



$display("For SUB opeartion");
a=1'b0;
b=1'b0;
Ainvert=1'b0;
Binvert=1'b1;
cy_in=1'b1;
op=2'b10;
$monitor("a=%b b=%b Ainvert=%b Binvert=%b carry in=%b op=%b result=%b zero_flag=%b",a,b,Ainvert,Binvert,cy_in,op,result,zero_flag);
#10;
a=1'b0;
b=1'b1;
Ainvert=1'b0;
Binvert=1'b1;
cy_in=1'b1;
op=2'b10;
$monitor("a=%b b=%b Ainvert=%b Binvert=%b carry in=%b op=%b result=%b zero_flag=%b",a,b,Ainvert,Binvert,cy_in,op,result,zero_flag);
#10;
a=1'b1;
b=1'b0;
Ainvert=1'b0;
Binvert=1'b1;
cy_in=1'b1;
op=2'b10;
$monitor("a=%b b=%b Ainvert=%b Binvert=%b carry in=%b op=%b result=%b zero_flag=%b",a,b,Ainvert,Binvert,cy_in,op,result,zero_flag);
#10;
a=1'b1;
b=1'b1;
Ainvert=1'b0;
Binvert=1'b1;
cy_in=1'b1;
op=2'b10;
$monitor("a=%b b=%b Ainvert=%b Binvert=%b carry in=%b op=%b result=%b zero_flag=%b\n",a,b,Ainvert,Binvert,cy_in,op,result,zero_flag);
#10;




//Inputs set to perform NAND Operation




$display("For NAND opeartion");
a=1'b0;
b=1'b0;
Ainvert=1'b1;
Binvert=1'b1;
op=2'b01;
$monitor("a=%b b=%b Ainvert=%b Binvert=%b op=%b result=%b zero_flag=%b",a,b,Ainvert,Binvert,op,result,zero_flag);
#10;
a=1'b0;
b=1'b1;
Ainvert=1'b1;
Binvert=1'b1;
op=2'b01;
$monitor("a=%b b=%b Ainvert=%b Binvert=%b op=%b result=%b zero_flag=%b",a,b,Ainvert,Binvert,op,result,zero_flag);
#10;
a=1'b1;
b=1'b0;
Ainvert=1'b1;
Binvert=1'b1;
op=2'b01;
$monitor("a=%b b=%b Ainvert=%b Binvert=%b op=%b result=%b zero_flag=%b",a,b,Ainvert,Binvert,op,result,zero_flag);
#10;
a=1'b1;
b=1'b1;
Ainvert=1'b1;
Binvert=1'b1;
op=2'b01;
$monitor("a=%b b=%b Ainvert=%b Binvert=%b op=%b result=%b zero_flag=%b\n",a,b,Ainvert,Binvert,op,result,zero_flag);
#10;





//Inputs set to perform NOR Operation






$display("For NOR operation");
a=1'b0;
b=1'b0;
Ainvert=1'b1;
Binvert=1'b1;
op=2'b00;
$monitor("a=%b b=%b Ainvert=%b Binvert=%b op=%b result=%b zero_flag=%b",a,b,Ainvert,Binvert,op,result,zero_flag);
#10;
a=1'b0;
b=1'b1;
Ainvert=1'b1;
Binvert=1'b1;
op=2'b00;
$monitor("a=%b b=%b Ainvert=%b Binvert=%b op=%b result=%b zero_flag=%b",a,b,Ainvert,Binvert,op,result,zero_flag);
#10;
a=1'b1;
b=1'b0;
Ainvert=1'b1;
Binvert=1'b1;
op=2'b00;
$monitor("a=%b b=%b Ainvert=%b Binvert=%b op=%b result=%b zero_flag=%b",a,b,Ainvert,Binvert,op,result,zero_flag);
#10;
a=1'b1;
b=1'b1;
Ainvert=1'b1;
Binvert=1'b1;
op=2'b00;
$monitor("a=%b b=%b Ainvert=%b Binvert=%b op=%b result=%b zero_flag=%b\n",a,b,Ainvert,Binvert,op,result,zero_flag);
#10;



//Inputs set to determine whether a>b 



$display("To get the result when a>b");
a=1'b0;
b=1'b0;
Ainvert=1'b1;
Binvert=1'b0;
cy_in=1'b1;
op=2'b11;
$monitor("a=%b b=%b Ainvert=%b Binvert=%b carry in=%b op=%b result=%b",a,b,Ainvert,Binvert,cy_in,op,result);
#10;
a=1'b0;
b=1'b1;
Ainvert=1'b1;
Binvert=1'b0;
cy_in=1'b1;
op=2'b11;
$monitor("a=%b b=%b Ainvert=%b Binvert=%b carry in=%b op=%b result=%b",a,b,Ainvert,Binvert,cy_in,op,result);
#10;
a=1'b1;
b=1'b0;
Ainvert=1'b1;
Binvert=1'b0;
cy_in=1'b1;
op=2'b11;
$monitor("a=%b b=%b Ainvert=%b Binvert=%b carry in=%b op=%b result=%b",a,b,Ainvert,Binvert,cy_in,op,result);
#10;
a=1'b1;
b=1'b1;
Ainvert=1'b1;
Binvert=1'b0;
cy_in=1'b1;
op=2'b11;
$monitor("a=%b b=%b Ainvert=%b Binvert=%b carry in=%b op=%b result=%b\n",a,b,Ainvert,Binvert,cy_in,op,result);
#10;
end

endmodule

A2/ALU/ALU.vcd
$date
	Sun Oct 29 22:40:15 2017
$end
$version
	Icarus Verilog
$end
$timescale
	1ps
$end
$scope module test $end
$var wire 1 ! zero_flag $end
$var wire 1 " result $end
$var reg 1 # Ainvert $end
$var reg 1 $ Binvert $end
$var reg 1 % a $end
$var reg 1 & b $end
$var reg 1 ' cy_in $end
$var reg 2 ( op [1:0] $end
$scope module f5 $end
$var wire 1 # Ainvert $end
$var wire 1 $ Binvert $end
$var wire 1 ) _and $end
$var wire 1 * _or $end
$var wire 1 % a $end
$var wire 1 & b $end
$var wire 1 ' cy_in $end
$var wire 2 + op [1:0] $end
$var wire 1 , t $end
$var wire 1 ! zero_flag $end
$var wire 1 " result $end
$var wire 1 - less1 $end
$var wire 1 . less $end
$var wire 1 / _sum $end
$var wire 1 0 _carry $end
$var wire 1 1 _b $end
$var wire 1 2 _a $end
$scope module f1 $end
$var wire 1 % a1 $end
$var wire 1 3 a2 $end
$var wire 1 2 o $end
$var wire 1 # select $end
$var wire 1 4 t1 $end
$var wire 1 5 t2 $end
$upscope $end
$scope module f2 $end
$var wire 1 & a1 $end
$var wire 1 6 a2 $end
$var wire 1 1 o $end
$var wire 1 $ select $end
$var wire 1 7 t1 $end
$var wire 1 8 t2 $end
$upscope $end
$scope module f3 $end
$var wire 1 2 a $end
$var wire 1 1 b $end
$var wire 1 ' cy_in $end
$var wire 1 0 cy_out $end
$var wire 1 9 t3 $end
$var wire 1 : t2 $end
$var wire 1 ; t1 $end
$var wire 1 / sum $end
$scope module G1 $end
$var wire 1 2 a $end
$var wire 1 1 b $end
$var wire 1 : cy_out $end
$var wire 1 ; sum $end
$upscope $end
$scope module G2 $end
$var wire 1 ; a $end
$var wire 1 ' b $end
$var wire 1 9 cy_out $end
$var wire 1 / sum $end
$upscope $end
$upscope $end
$scope module f4 $end
$var wire 1 % a $end
$var wire 1 & b $end
$var wire 1 < cy_in $end
$var wire 1 , cy_out $end
$var wire 1 = t3 $end
$var wire 1 > t2 $end
$var wire 1 ? t1 $end
$var wire 1 - sum $end
$scope module G1 $end
$var wire 1 % a $end
$var wire 1 & b $end
$var wire 1 > cy_out $end
$var wire 1 ? sum $end
$upscope $end
$scope module G2 $end
$var wire 1 ? a $end
$var wire 1 < b $end
$var wire 1 = cy_out $end
$var wire 1 - sum $end
$upscope $end
$upscope $end
$scope module f5 $end
$var wire 1 ) a1 $end
$var wire 1 * a2 $end
$var wire 1 / a3 $end
$var wire 1 " o $end
$var wire 2 @ select [1:0] $end
$var wire 1 A t1 $end
$var wire 1 B t2 $end
$var wire 1 C t3 $end
$var wire 1 D t4 $end
$var wire 1 . a4 $end
$upscope $end
$scope module f6 $end
$var wire 1 2 a $end
$var wire 1 1 b $end
$var wire 1 E cy_in $end
$var wire 1 , cy_out $end
$var wire 1 F t3 $end
$var wire 1 G t2 $end
$var wire 1 H t1 $end
$var wire 1 . sum $end
$scope module G1 $end
$var wire 1 2 a $end
$var wire 1 1 b $end
$var wire 1 G cy_out $end
$var wire 1 H sum $end
$upscope $end
$scope module G2 $end
$var wire 1 H a $end
$var wire 1 E b $end
$var wire 1 F cy_out $end
$var wire 1 . sum $end
$upscope $end
$upscope $end
$upscope $end
$upscope $end
$enddefinitions $end
#0
$dumpvars
0H
0G
0F
1E
1D
1C
1B
1A
b0 @
0?
0>
0=
1<
0;
0:
09
18
17
16
15
14
13
02
01
00
x/
1.
1-
0,
b0 +
0*
0)
b0 (
x'
0&
0%
0$
0#
0"
1!
$end
#10000
x0
x9
0.
1F
1;
1H
1*
0!
1,
11
0-
1=
06
07
1?
1&
#20000
01
12
16
17
03
04
0&
1%
#30000
1"
09
10
1.
0F
0A
0;
1:
0H
1G
1)
1!
11
1-
0=
06
07
0?
1>
1&
#40000
0"
00
1A
0:
0G
0*
0)
1B
01
02
0,
16
17
13
14
0>
b1 (
b1 +
b1 @
0&
0%
#50000
x0
1"
x9
0.
1F
0B
1;
1H
1*
0!
1,
11
0-
1=
06
07
1?
1&
#60000
01
12
16
17
03
04
0&
1%
#70000
09
10
1.
0F
0;
1:
0H
1G
1)
1!
11
1-
0=
06
07
0?
1>
1&
#80000
00
0"
0:
0G
0*
0)
1B
01
02
0,
0/
16
17
13
14
0>
b10 (
b10 +
b10 @
0'
0&
0%
#90000
1"
0C
1/
0.
1F
1;
1H
1*
0!
1,
11
0-
1=
06
07
1?
1&
#100000
01
12
16
17
03
04
0&
1%
#110000
0"
1C
0/
10
1.
0F
0;
1:
0H
1G
1)
1!
11
1-
0=
06
07
0?
1>
1&
#120000
19
10
0.
1F
0"
1;
0:
1H
0G
0)
1C
02
x,
0/
08
16
17
13
14
0>
1'
1$
0&
0%
#130000
1"
0C
00
1/
09
1.
0F
0;
0H
0*
01
0!
x,
18
0-
1=
06
1?
1&
#140000
1"
0C
10
1,
1:
1G
1)
1/
09
1.
0F
11
0;
0H
1*
08
12
16
03
04
0&
1%
#150000
0"
1C
0/
19
10
0.
1F
1,
1;
0:
1H
0G
0)
01
1!
18
1-
0=
06
0?
1>
1&
#160000
1/
09
1.
0F
1"
0;
1:
0H
1G
1)
0B
11
08
x,
05
16
13
14
0>
b1 (
b1 +
b1 @
1#
0&
0%
#170000
0/
19
10
0.
1F
1;
0:
1H
0G
0)
01
0!
1,
18
0-
1=
06
1?
1&
#180000
11
02
08
15
16
03
0&
1%
#190000
00
x,
0"
1/
09
1.
0F
1B
0;
0H
0*
01
1!
18
1-
0=
06
0?
1>
1&
#200000
1"
10
0A
1:
1G
1*
1)
11
12
08
05
x,
16
13
0>
b0 (
b0 +
b0 @
0&
0%
#210000
0"
0/
19
10
0.
1F
1A
1;
0:
1H
0G
0)
01
0!
1,
18
0-
1=
06
1?
1&
#220000
11
02
08
15
16
03
0&
1%
#230000
00
x,
1/
09
1.
0F
0;
0H
0*
01
1!
18
1-
0=
06
0?
1>
1&
#240000
10
0/
19
0.
1F
1;
1H
1*
0"
12
1D
05
x,
16
13
0>
b11 (
b11 +
b11 @
0$
0&
0%
#250000
1"
0D
1/
09
1.
0F
0;
1:
0H
1G
1)
0!
1,
11
0-
1=
06
07
1?
1&
#260000
00
x,
0:
0G
0*
0)
02
01
15
16
17
03
0&
1%
#270000
0"
10
1D
1,
0/
19
0.
1F
1;
1H
1*
1!
11
1-
0=
06
07
0?
1>
1&
